agentfail/__init__.py
agentfail/client.py
agentfail-0.1.0.dist-info/METADATA
agentfail-0.1.0.dist-info/WHEEL
agentfail-0.1.0.dist-info/top_level.txt
agentfail-0.1.0.dist-info/RECORD
